{
  "generated_at_utc": "2026-06-16T16:26:40.479809+02:00",
  "regression_candidate": {
    "model_family": "cnn_bilstm",
    "model_type": "CNN_BiLSTM",
    "run_id": "673ffb5e04cf43fcba5b55a6a4422737",
    "run_name": "cnn_bilstm_regression_stride5_full_cnn_bilstm_best_sweep_none",
    "feature_set": "full",
    "dataset_group": "no_quiet",
    "input_npz": "data\\preprocessing\\processed_stride5\\volcano_multi.npz",
    "loss_weighting": "none",
    "early_stopping_metric": "business_score",
    "test_business_score": 5.156843996047974,
    "test_mae": 5.255398273468018,
    "test_rmse": 6.482221204336008,
    "test_r2": 0.7625662088394165,
    "test_mae_36_48h": 4.584619522094727,
    "test_mae_24_36h": 5.655839920043945,
    "test_mae_12_24h": 6.054703712463379,
    "test_mae_6_12h": 4.238229751586914,
    "test_mae_0_6h": 5.000359535217285,
    "status": "candidate_exploratory",
    "note": "Bonne performance sur split fixe. La robustesse inter-éruption doit être interprétée à partir du LOO.",
    "loo_summary_csv": "reports\\loo_regression_summary\\loo_regression_summary.csv",
    "loo_status": "available"
  },
  "classification_candidate": {
    "selection_name": "cnn_transformer_alert_priority",
    "model_family": "cnn_transformer",
    "task_type": "classification",
    "feature_set": "full",
    "dataset_group": "with_quiet",
    "alert_threshold_24h": 0.35,
    "min_class_alert": 3,
    "selection_min_recall": 0.8,
    "selection_status": "eligible",
    "precision_alert_24h": 0.6444241316270567,
    "recall_alert_24h": 0.8159722222222222,
    "f1_alert_24h": 0.7201225740551583,
    "tp": 705,
    "fp": 389,
    "fn": 159,
    "tn": 1247,
    "source_csv": "reports\\threshold_optimization\\cnn_transformer_alert_priority\\threshold_scan_alert_24h.csv",
    "status": "selected_for_alerting",
    "run_id": "5400525d69fe49029a27f3c36faa29bf",
    "run_name": "cnn_transformer_classification_with_quiet_stride5_full_cnn_transformer_medium_alert_priority",
    "model_type": "CNNTransformerClassifier",
    "input_npz": "data\\preprocessing\\processed_full_stride5_with_quiet\\volcano_multi.npz",
    "class_weighting": "alert_priority",
    "label_smoothing": 0.0,
    "early_stopping_metric": "business_score_classification",
    "test_business_score_classification": 0.2189004124277527,
    "test_macro_f1": 0.109737744582048,
    "test_balanced_accuracy": 0.1922203052092163,
    "test_class_0_f1": 0.1617486338797814,
    "test_class_1_f1": 0.2103174603174603,
    "test_class_2_f1": 0.057788944723618,
    "test_class_3_f1": 0.0,
    "test_class_4_f1": 0.0,
    "test_class_5_f1": 0.2285714285714285,
    "training_run_id": "42cc5dd5722349c88b056eb3c6b77d63",
    "checkpoint_artifact": "best_cnn_transformer_classifier.pt",
    "model_class": "scripts.training.train_cnn_transformer_classif:CNNTransformerClassifier",
    "model_export_run_id": "5400525d69fe49029a27f3c36faa29bf",
    "mlflow_run_model_uri": "runs:/5400525d69fe49029a27f3c36faa29bf/model",
    "s3_model_uri": "s3://vulcadata/models/champion_classification_model",
    "source_checkpoint_uri": "runs:/42cc5dd5722349c88b056eb3c6b77d63/best_cnn_transformer_classifier.pt",
    "feature_dim": 992,
    "n_classes": 6,
    "model_uri": "s3://vulcadata/models/champion_classification_checkpoint/best_cnn_transformer_classifier.pt",
    "flavor": "pytorch_checkpoint",
    "runtime_model_source": "s3_direct_pytorch_checkpoint",
    "s3_checkpoint_uri": "s3://vulcadata/models/champion_classification_checkpoint/best_cnn_transformer_classifier.pt",
    "artifact_path": "models/champion_classification_checkpoint/best_cnn_transformer_classifier.pt",
    "previous_pyfunc_model_uri": "s3://vulcadata/models/champion_classification_model",
    "previous_pyfunc_s3_model_uri": "s3://vulcadata/models/champion_classification_model",
    "previous_runtime_model_source": "s3_direct_pyfunc_model",
    "d_model": 96,
    "nhead": 4,
    "num_layers": 3,
    "dim_feedforward": 256,
    "dropout": 0.2,
    "input_noise_std": 0.01
  },
  "decision": {
    "main_operational_model": "classification_candidate",
    "regression_role": "exploratory_time_to_eruption_estimation",
    "classification_role": "operational_alert_24h",
    "rationale": "La classification est retenue comme modèle opérationnel principal car elle correspond mieux à l'objectif d'alerte. La régression est conservée comme estimation exploratoire du délai avant éruption."
  },
  "sources": {
    "threshold_winner_json": "reports\\threshold_optimization\\comparison\\threshold_comparison_winner.json",
    "threshold_all_results_csv": "reports\\threshold_optimization\\comparison\\threshold_comparison_all_results.csv",
    "threshold_best_by_model_csv": "reports\\threshold_optimization\\comparison\\threshold_comparison_best_by_model.csv"
  },
  "mlflow_model_export": {
    "source_training_run_id": "42cc5dd5722349c88b056eb3c6b77d63",
    "checkpoint_artifact": "best_cnn_transformer_classifier.pt",
    "model_class": "scripts.training.train_cnn_transformer_classif:CNNTransformerClassifier",
    "export_run_id": "5400525d69fe49029a27f3c36faa29bf",
    "artifact_path": "models/champion_classification_model",
    "model_uri": "s3://vulcadata/models/champion_classification_model",
    "flavor": "pyfunc",
    "source_checkpoint_uri": "runs:/42cc5dd5722349c88b056eb3c6b77d63/best_cnn_transformer_classifier.pt",
    "s3_model_uri": "s3://vulcadata/models/champion_classification_model",
    "runtime_model_source": "deprecated_pyfunc_export_not_used_for_runtime",
    "deprecated_pyfunc_model_uri": "s3://vulcadata/models/champion_classification_model",
    "deprecated_pyfunc_s3_model_uri": "s3://vulcadata/models/champion_classification_model",
    "runtime_checkpoint_uri": "s3://vulcadata/models/champion_classification_checkpoint/best_cnn_transformer_classifier.pt",
    "note": "Runtime inference uses the direct PyTorch checkpoint on S3. The previous MLflow pyfunc export is kept only for traceability."
  }
}
